fukkatsu/__init__.py
fukkatsu/llm/__init__.py
fukkatsu/llm/gateway.py
fukkatsu/memory/__init__.py
fukkatsu/memory/short.py
fukkatsu/observer/__init__.py
fukkatsu/observer/tracker.py
fukkatsu/utils/__init__.py
fukkatsu/utils/helper.py
fukkatsu/utils/prompt.py
fukkatsu/utils/synthesize.py
fukkatsu-0.0.14.dist-info/LICENSE
fukkatsu-0.0.14.dist-info/METADATA
fukkatsu-0.0.14.dist-info/WHEEL
fukkatsu-0.0.14.dist-info/top_level.txt
fukkatsu-0.0.14.dist-info/RECORD
