Metadata-Version: 2.1
Name: fukkatsu
Version: 0.0.14
Summary: Dynamic Software Improvement and Mutation using LLMs for Stochastic Synthetic Code Injections.
Home-page: https://github.com/maxmekiska/fukkatsu
Author: Maximilian Mekiska
Author-email: maxmekiska@gmail.com
Keywords: machinelearning,llm,runtime,codecorrection
Classifier: Programming Language :: Python :: 3.9
Classifier: Programming Language :: Python :: 3.10
Classifier: Programming Language :: Python :: 3.11
Classifier: Programming Language :: Python :: 3.12
Classifier: Programming Language :: Python :: 3.13
Classifier: Topic :: Scientific/Engineering :: Artificial Intelligence
Requires-Python: >= 3.9.0, < 3.14.0
License-File: LICENSE
Requires-Dist: openai <=1.57.00,>=1.56.0
Requires-Dist: lz4 <=4.4.0,>=4.3.3
